README.txt
TGScriptaculous.kpf
setup.py
Scriptaculous.egg-info/PKG-INFO
Scriptaculous.egg-info/SOURCES.txt
Scriptaculous.egg-info/dependency_links.txt
Scriptaculous.egg-info/entry_points.txt
Scriptaculous.egg-info/not-zip-safe
Scriptaculous.egg-info/paster_plugins.txt
Scriptaculous.egg-info/requires.txt
Scriptaculous.egg-info/sqlobject.txt
Scriptaculous.egg-info/top_level.txt
scriptaculous/__init__.py
scriptaculous/release.py
scriptaculous/thirdparty.py
scriptaculous/widgets.py
scriptaculous/static/css/autocomplete.css
scriptaculous/static/css/thirdparty/control.rating.css
scriptaculous/static/css/thirdparty/modalbox.css
scriptaculous/static/css/thirdparty/ossdl.css
scriptaculous/static/css/thirdparty/password_strength.css
scriptaculous/static/css/thirdparty/tabs.css
scriptaculous/static/images/grid_foot.png
scriptaculous/static/images/grid_head.png
scriptaculous/static/images/nav_first.gif
scriptaculous/static/images/nav_grey_first.gif
scriptaculous/static/images/nav_grey_last.gif
scriptaculous/static/images/nav_grey_next.gif
scriptaculous/static/images/nav_grey_prev.gif
scriptaculous/static/images/nav_last.gif
scriptaculous/static/images/nav_next.gif
scriptaculous/static/images/nav_prev.gif
scriptaculous/static/images/reload.gif
scriptaculous/static/images/reload_grey.gif
scriptaculous/static/images/sort_asc.gif
scriptaculous/static/images/sort_desc.gif
scriptaculous/static/images/thirdparty/password_strength.jpg
scriptaculous/static/images/thirdparty/rating.gif
scriptaculous/static/images/thirdparty/spinner.gif
scriptaculous/static/images/thirdparty/tableft10.gif
scriptaculous/static/images/thirdparty/tabright10.gif
scriptaculous/static/javascript/builder.js
scriptaculous/static/javascript/controls.js
scriptaculous/static/javascript/dragdrop.js
scriptaculous/static/javascript/effects.js
scriptaculous/static/javascript/prototype.js
scriptaculous/static/javascript/scriptaculous.js
scriptaculous/static/javascript/slider.js
scriptaculous/static/javascript/sound.js
scriptaculous/static/javascript/unittest.js
scriptaculous/static/javascript/thirdparty/control.rating.js
scriptaculous/static/javascript/thirdparty/modalbox.js
scriptaculous/static/javascript/thirdparty/ossdl.js
scriptaculous/static/javascript/thirdparty/password_strength.js
scriptaculous/static/javascript/thirdparty/prototabs.js
