Metadata-Version: 1.0
Name: Scriptaculous
Version: 1.8.2
Summary: Scriptaculous packaged as TurboGears widgets.
Home-page: http://tgwidgets.ossdl.de/
Author: Thomas Fuchs, Sam Stephenson, Kevin Dangoor, Fred Lin, W-Mark Kubacki
Author-email: mark@ossdl.de
License: MIT
Download-URL: http://static.ossdl.de/tgwidgets/downloads/
Keywords: turbogears.widgets
Platform: UNKNOWN
Classifier: Development Status :: 4 - Beta
Classifier: Operating System :: OS Independent
Classifier: Programming Language :: Python
Classifier: Programming Language :: JavaScript
Classifier: Topic :: Software Development :: Libraries :: Python Modules
Classifier: Framework :: TurboGears
Classifier: Framework :: TurboGears :: Widgets
